{
  "title": "Kiteboarding Boston's Pleasure Bay May 4th, 2015",
  "metaTags": [
    {
      "name": "description",
      "content": "Local Boston kitesurfers enjoying a nice windy Spring day at one of New England's best kiteboarding spots, Pleasure Bay on May 4th, 2015"
    },
    {
      "itemprop": "name",
      "content": "Kiteboarding Boston's Pleasure Bay May 4th, 2015"
    },
    {
      "itemprop": "description",
      "content": "Local Boston kitesurfers enjoying a nice windy Spring day at one of New England's best kiteboarding spots, Pleasure Bay on May 4th, 2015"
    },
    {
      "name": "twitter:card",
      "content": "summary_large_image"
    },
    {
      "name": "twitter:site",
      "content": "@kfinley"
    },
    {
      "name": "twitter:creator",
      "content": "@kfinley"
    },
    {
      "name": "twitter:title",
      "content": "Kiteboarding Boston's Pleasure Bay May 4th, 2015"
    },
    {
      "name": "twitter:description",
      "content": "Local Boston kitesurfers enjoying a nice windy Spring day at one of New England's best kiteboarding spots, Pleasure Bay on May 4th, 2015"
    },
    {
      "name": "twitter:image:src",
      "content": "https://KyleFinley.net/img/copyrighted/%C2%A9_Kyle_Finley_2015.05.04-Kiteboarding_Pleasure_Bay-IMG_3016.jpg"
    },
    {
      "property": "twitter:account_id",
      "content": "1530436921"
    },
    {
      "property": "og:title",
      "content": "Kiteboarding Boston's Pleasure Bay May 4th, 2015"
    },
    {
      "property": "og:type",
      "content": "Website"
    },
    {
      "property": "og:url",
      "content": "https://KyleFinley.net/kiteboarding-boston-pleasure-bay-20150504"
    },
    {
      "property": "og:image",
      "content": "https://KyleFinley.net/img/copyrighted/%C2%A9_Kyle_Finley_2015.05.04-Kiteboarding_Pleasure_Bay-IMG_3016.jpg"
    },
    {
      "property": "og:description",
      "content": "Local Boston kitesurfers enjoying a nice windy Spring day at one of New England's best kiteboarding spots, Pleasure Bay on May 4th, 2015"
    },
    {
      "property": "og:site_name",
      "content": "KyleFinley.net"
    },
    {
      "property": "article:published_time",
      "content": "5/6/2015 12:16:54 PM"
    },
    {
      "property": "article:modified_time",
      "content": "6/7/2015 7:41:14 AM"
    },
    {
      "property": "article:author",
      "content": "Kyle Finley"
    }
  ]
}
